<?xml version="1.0"?>
<!DOCTYPE hibernate-mapping PUBLIC "-//Hibernate/Hibernate Mapping DTD 3.0//EN"
"http://hibernate.sourceforge.net/hibernate-mapping-3.0.dtd">
<!-- Generated 2016-5-24 9:55:27 by Hibernate Tools 3.5.0.Final -->
<hibernate-mapping>
    <class name="entity.GoodsDeSearch" table="GOODSDESEARCH">
        <id name="gid" type="int" access="field">
            <column name="GID" />
            <generator class="assigned" />
        </id>
        <property name="chinaName" type="java.lang.String" access="field">
            <column name="CHINANAME" />
        </property>
        <property name="tableName" type="java.lang.String" access="field">
            <column name="TABLENAME" />
        </property>
    </class>
</hibernate-mapping>
